pysimons
tests
