Metadata-Version: 2.1
Name: PySimons
Version: 0.1.0
Summary: A package which expands on the tools provided by pyfinance
Home-page: https://github.com/yourusername/finance_tools
Author: Zachary Fagnou
Author-email: zfagnou3@gmail.com
Classifier: Programming Language :: Python :: 3
Classifier: License :: OSI Approved :: MIT License
Classifier: Operating System :: OS Independent
Requires-Python: >=3.6
